Cargo.toml
README.md
zkbp/__init__.py
zkbp/zkbp.pyd
zkbp-0.1.5.dist-info/licenses/LICENSE
zkbp-0.1.5.dist-info/METADATA
zkbp-0.1.5.dist-info/WHEEL
zkbp-0.1.5.dist-info/RECORD
