Metadata-Version: 2.4
Name: zkbp
Version: 0.1.5
Classifier: Development Status :: 5 - Production/Stable
Classifier: Intended Audience :: Developers
Classifier: License :: OSI Approved :: Apache Software License
Classifier: Operating System :: MacOS
Classifier: Operating System :: Microsoft :: Windows
Classifier: Operating System :: POSIX :: Linux
Classifier: Programming Language :: Python :: 3
Classifier: Programming Language :: Python :: 3.9
Classifier: Programming Language :: Python :: 3.10
Classifier: Programming Language :: Python :: 3.11
Classifier: Programming Language :: Python :: Implementation :: CPython
Classifier: Programming Language :: Python
Classifier: Programming Language :: Rust
Classifier: Typing :: Typed
Summary: ZKBP Python bindings
Keywords: zk,crypto,bn254
Author: JP Morgan Chase
License: Apache-2.0
Requires-Python: >=3.9
Project-URL: Source Code, https://github.com/jpmorganchase/padl
